ioctf/__init__.py
ioctf/ioctf.py
ioctf-0.1.1.dist-info/LICENSE
ioctf-0.1.1.dist-info/METADATA
ioctf-0.1.1.dist-info/WHEEL
ioctf-0.1.1.dist-info/top_level.txt
ioctf-0.1.1.dist-info/RECORD
